libraryPDB/PDBdescriptors.py
libraryPDB/PDBio_utils.py
libraryPDB/PDBparser.py
libraryPDB/PDBquality.py
libraryPDB/PDBsearch_utils.py
libraryPDB/PDBsummary.py
libraryPDB/__init__.py
librarypdb-0.1.3.dist-info/licenses/LICENSE.txt
librarypdb-0.1.3.dist-info/METADATA
librarypdb-0.1.3.dist-info/WHEEL
librarypdb-0.1.3.dist-info/top_level.txt
librarypdb-0.1.3.dist-info/RECORD
