Metadata-Version: 2.4
Name: libraryPDB
Version: 0.1.3
Summary: Lightweight Python library for large-scale PDB structural analysis
Home-page: https://github.com/CJ438837/libraryPDB
Author: Cédric Jadot
Author-email: Jadot Cédric <cedricjadot@msn.com>
Project-URL: Homepage, https://github.com/CJ438837/libraryPDB
Requires-Python: >=3.8
License-File: LICENSE.txt
Requires-Dist: requests
Dynamic: author
Dynamic: home-page
Dynamic: license-file
